odoo/addons/l10n_th_gov_account_asset_management/README.rst
odoo/addons/l10n_th_gov_account_asset_management/__init__.py
odoo/addons/l10n_th_gov_account_asset_management/__manifest__.py
odoo/addons/l10n_th_gov_account_asset_management/data/ir_actions_server_data.xml
odoo/addons/l10n_th_gov_account_asset_management/i18n/l10n_th_gov_account_asset_management.pot
odoo/addons/l10n_th_gov_account_asset_management/models/__init__.py
odoo/addons/l10n_th_gov_account_asset_management/models/account_asset.py
odoo/addons/l10n_th_gov_account_asset_management/models/account_asset_line.py
odoo/addons/l10n_th_gov_account_asset_management/models/account_asset_location.py
odoo/addons/l10n_th_gov_account_asset_management/models/account_asset_maintenance.py
odoo/addons/l10n_th_gov_account_asset_management/models/account_move.py
odoo/addons/l10n_th_gov_account_asset_management/models/purchase.py
odoo/addons/l10n_th_gov_account_asset_management/models/res_company.py
odoo/addons/l10n_th_gov_account_asset_management/models/res_config_settings.py
odoo/addons/l10n_th_gov_account_asset_management/readme/CONTRIBUTORS.rst
odoo/addons/l10n_th_gov_account_asset_management/readme/DESCRIPTION.rst
odoo/addons/l10n_th_gov_account_asset_management/readme/HISTORY.rst
odoo/addons/l10n_th_gov_account_asset_management/security/ir.model.access.csv
odoo/addons/l10n_th_gov_account_asset_management/static/description/icon.png
odoo/addons/l10n_th_gov_account_asset_management/static/description/index.html
odoo/addons/l10n_th_gov_account_asset_management/tests/__init__.py
odoo/addons/l10n_th_gov_account_asset_management/tests/test_gov_account_asset_management.py
odoo/addons/l10n_th_gov_account_asset_management/views/account_asset_location_views.xml
odoo/addons/l10n_th_gov_account_asset_management/views/account_asset_views.xml
odoo/addons/l10n_th_gov_account_asset_management/views/account_move.xml
odoo/addons/l10n_th_gov_account_asset_management/views/purchase_views.xml
odoo_addon_l10n_th_gov_account_asset_management-15.0.3.0.1.dist-info/METADATA
odoo_addon_l10n_th_gov_account_asset_management-15.0.3.0.1.dist-info/WHEEL
odoo_addon_l10n_th_gov_account_asset_management-15.0.3.0.1.dist-info/top_level.txt
odoo_addon_l10n_th_gov_account_asset_management-15.0.3.0.1.dist-info/RECORD
