Metadata-Version: 2.1
Name: odoo-addon-l10n_th_gov_account_asset_management
Version: 15.0.3.0.1
Summary: Thai Localization - Government Assets Management
Home-page: https://github.com/OCA/l10n-thailand
Author: Ecosoft, Odoo Community Association (OCA)
Author-email: support@odoo-community.org
License: AGPL-3
Classifier: Programming Language :: Python
Classifier: Framework :: Odoo
Classifier: Framework :: Odoo :: 15.0
Classifier: License :: OSI Approved :: GNU Affero General Public License v3
Classifier: Development Status :: 3 - Alpha
Requires-Python: >=3.8
Requires-Dist: odoo-addon-account-asset-low-value<15.1dev,>=15.0dev
Requires-Dist: odoo-addon-account-asset-transfer<15.1dev,>=15.0dev
Requires-Dist: odoo-addon-l10n-th-account-asset-management<15.1dev,>=15.0dev
Requires-Dist: odoo-addon-purchase-work-acceptance<15.1dev,>=15.0dev
Requires-Dist: odoo<15.1dev,>=15.0a
